[1,["98l5e2LI9C5acIvTT+pkcp","1d6b1e5ab"],["spriteFrame","_textureSetter"],["cc.SpriteFrame",["cc.BitmapFont",["_name","fontSize","_fntConfig"],0]],[[1,0,1,2,4]],[[[[0,"skin-font",40,{"commonHeight":46,"fontSize":40,"atlasName":"skin-font.png","fontDefDictionary":{"32":{"xOffset":0,"yOffset":38,"xAdvance":10,"rect":{"x":59,"y":457,"width":0,"height":0}},"33":{"xOffset":2,"yOffset":-4,"xAdvance":12,"rect":{"x":265,"y":340,"width":18,"height":42}},"34":{"xOffset":0,"yOffset":-4,"xAdvance":13,"rect":{"x":221,"y":421,"width":22,"height":22}},"35":{"xOffset":-1,"yOffset":-4,"xAdvance":21,"rect":{"x":227,"y":252,"width":34,"height":42}},"36":{"xOffset":-1,"yOffset":-7,"xAdvance":19,"rect":{"x":319,"y":109,"width":31,"height":48}},"37":{"xOffset":0,"yOffset":-5,"xAdvance":30,"rect":{"x":267,"y":160,"width":40,"height":43}},"38":{"xOffset":-1,"yOffset":-4,"xAdvance":27,"rect":{"x":287,"y":207,"width":37,"height":42}},"39":{"xOffset":0,"yOffset":-4,"xAdvance":8,"rect":{"x":267,"y":421,"width":17,"height":22}},"40":{"xOffset":1,"yOffset":-5,"xAdvance":10,"rect":{"x":352,"y":109,"width":19,"height":47}},"41":{"xOffset":0,"yOffset":-5,"xAdvance":10,"rect":{"x":373,"y":109,"width":19,"height":47}},"42":{"xOffset":0,"yOffset":-5,"xAdvance":15,"rect":{"x":130,"y":421,"width":26,"height":28}},"43":{"xOffset":0,"yOffset":4,"xAdvance":24,"rect":{"x":2,"y":421,"width":34,"height":34}},"44":{"xOffset":-1,"yOffset":21,"xAdvance":10,"rect":{"x":245,"y":421,"width":20,"height":22}},"45":{"xOffset":0,"yOffset":13,"xAdvance":24,"rect":{"x":371,"y":421,"width":34,"height":17}},"46":{"xOffset":1,"yOffset":21,"xAdvance":10,"rect":{"x":2,"y":457,"width":18,"height":17}},"47":{"xOffset":-1,"yOffset":-4,"xAdvance":16,"rect":{"x":67,"y":340,"width":28,"height":42}},"48":{"xOffset":-1,"yOffset":-4,"xAdvance":21,"rect":{"x":2,"y":296,"width":32,"height":42}},"49":{"xOffset":-1,"yOffset":-4,"xAdvance":14,"rect":{"x":241,"y":340,"width":22,"height":42}},"50":{"xOffset":0,"yOffset":-4,"xAdvance":21,"rect":{"x":169,"y":296,"width":31,"height":42}},"51":{"xOffset":0,"yOffset":-4,"xAdvance":21,"rect":{"x":202,"y":296,"width":31,"height":42}},"52":{"xOffset":-2,"yOffset":-4,"xAdvance":21,"rect":{"x":335,"y":252,"width":33,"height":42}},"53":{"xOffset":0,"yOffset":-4,"xAdvance":21,"rect":{"x":235,"y":296,"width":31,"height":42}},"54":{"xOffset":0,"yOffset":-4,"xAdvance":21,"rect":{"x":268,"y":296,"width":31,"height":42}},"55":{"xOffset":-1,"yOffset":-4,"xAdvance":20,"rect":{"x":70,"y":296,"width":31,"height":42}},"56":{"xOffset":0,"yOffset":-4,"xAdvance":21,"rect":{"x":301,"y":296,"width":31,"height":42}},"57":{"xOffset":0,"yOffset":-4,"xAdvance":21,"rect":{"x":334,"y":296,"width":31,"height":42}},"58":{"xOffset":1,"yOffset":7,"xAdvance":10,"rect":{"x":110,"y":421,"width":18,"height":31}},"59":{"xOffset":-1,"yOffset":7,"xAdvance":10,"rect":{"x":349,"y":340,"width":20,"height":36}},"60":{"xOffset":0,"yOffset":4,"xAdvance":24,"rect":{"x":38,"y":421,"width":34,"height":34}},"61":{"xOffset":0,"yOffset":9,"xAdvance":24,"rect":{"x":158,"y":421,"width":34,"height":25}},"62":{"xOffset":0,"yOffset":4,"xAdvance":24,"rect":{"x":74,"y":421,"width":34,"height":34}},"63":{"xOffset":-1,"yOffset":-4,"xAdvance":18,"rect":{"x":35,"y":340,"width":30,"height":42}},"64":{"xOffset":-1,"yOffset":-4,"xAdvance":32,"rect":{"x":162,"y":207,"width":43,"height":42}},"65":{"xOffset":-2,"yOffset":-4,"xAdvance":24,"rect":{"x":326,"y":207,"width":37,"height":42}},"66":{"xOffset":0,"yOffset":-4,"xAdvance":21,"rect":{"x":103,"y":296,"width":31,"height":42}},"67":{"xOffset":-1,"yOffset":-4,"xAdvance":24,"rect":{"x":116,"y":252,"width":35,"height":42}},"68":{"xOffset":0,"yOffset":-4,"xAdvance":25,"rect":{"x":153,"y":252,"width":35,"height":42}},"69":{"xOffset":0,"yOffset":-4,"xAdvance":18,"rect":{"x":127,"y":340,"width":27,"height":42}},"70":{"xOffset":0,"yOffset":-4,"xAdvance":16,"rect":{"x":156,"y":340,"width":27,"height":42}},"71":{"xOffset":-1,"yOffset":-4,"xAdvance":27,"rect":{"x":207,"y":207,"width":38,"height":42}},"72":{"xOffset":0,"yOffset":-4,"xAdvance":27,"rect":{"x":2,"y":252,"width":36,"height":42}},"73":{"xOffset":0,"yOffset":-4,"xAdvance":8,"rect":{"x":305,"y":340,"width":17,"height":42}},"74":{"xOffset":-2,"yOffset":-4,"xAdvance":15,"rect":{"x":213,"y":340,"width":26,"height":42}},"75":{"xOffset":0,"yOffset":-4,"xAdvance":23,"rect":{"x":263,"y":252,"width":34,"height":42}},"76":{"xOffset":0,"yOffset":-4,"xAdvance":15,"rect":{"x":185,"y":340,"width":26,"height":42}},"77":{"xOffset":-1,"yOffset":-4,"xAdvance":33,"rect":{"x":115,"y":207,"width":45,"height":42}},"78":{"xOffset":0,"yOffset":-4,"xAdvance":27,"rect":{"x":40,"y":252,"width":36,"height":42}},"79":{"xOffset":-1,"yOffset":-4,"xAdvance":27,"rect":{"x":247,"y":207,"width":38,"height":42}},"80":{"xOffset":0,"yOffset":-4,"xAdvance":21,"rect":{"x":36,"y":296,"width":32,"height":42}},"81":{"xOffset":-1,"yOffset":-5,"xAdvance":27,"rect":{"x":309,"y":160,"width":40,"height":43}},"82":{"xOffset":0,"yOffset":-4,"xAdvance":21,"rect":{"x":367,"y":296,"width":31,"height":42}},"83":{"xOffset":-1,"yOffset":-4,"xAdvance":19,"rect":{"x":136,"y":296,"width":31,"height":42}},"84":{"xOffset":-2,"yOffset":-4,"xAdvance":18,"rect":{"x":2,"y":340,"width":31,"height":42}},"85":{"xOffset":0,"yOffset":-4,"xAdvance":27,"rect":{"x":78,"y":252,"width":36,"height":42}},"86":{"xOffset":-2,"yOffset":-4,"xAdvance":22,"rect":{"x":190,"y":252,"width":35,"height":42}},"87":{"xOffset":-1,"yOffset":-4,"xAdvance":33,"rect":{"x":68,"y":207,"width":45,"height":42}},"88":{"xOffset":-2,"yOffset":-4,"xAdvance":24,"rect":{"x":365,"y":207,"width":37,"height":42}},"89":{"xOffset":-2,"yOffset":-4,"xAdvance":20,"rect":{"x":370,"y":252,"width":33,"height":42}},"90":{"xOffset":-1,"yOffset":-4,"xAdvance":22,"rect":{"x":299,"y":252,"width":34,"height":42}},"91":{"xOffset":1,"yOffset":-4,"xAdvance":10,"rect":{"x":28,"y":160,"width":20,"height":45}},"92":{"xOffset":-1,"yOffset":-4,"xAdvance":16,"rect":{"x":97,"y":340,"width":28,"height":42}},"93":{"xOffset":-2,"yOffset":-4,"xAdvance":10,"rect":{"x":50,"y":160,"width":20,"height":45}},"94":{"xOffset":-4,"yOffset":-5,"xAdvance":8,"rect":{"x":320,"y":421,"width":25,"height":19}},"95":{"xOffset":-3,"yOffset":27,"xAdvance":20,"rect":{"x":22,"y":457,"width":35,"height":16}},"96":{"xOffset":-2,"yOffset":-5,"xAdvance":8,"rect":{"x":347,"y":421,"width":22,"height":19}},"97":{"xOffset":-1,"yOffset":3,"xAdvance":22,"rect":{"x":46,"y":384,"width":32,"height":35}},"98":{"xOffset":0,"yOffset":-6,"xAdvance":22,"rect":{"x":72,"y":160,"width":32,"height":44}},"99":{"xOffset":-1,"yOffset":3,"xAdvance":18,"rect":{"x":340,"y":384,"width":29,"height":35}},"100":{"xOffset":-1,"yOffset":-6,"xAdvance":22,"rect":{"x":106,"y":160,"width":32,"height":44}},"101":{"xOffset":-1,"yOffset":3,"xAdvance":21,"rect":{"x":80,"y":384,"width":32,"height":35}},"102":{"xOffset":-2,"yOffset":-6,"xAdvance":10,"rect":{"x":203,"y":160,"width":24,"height":44}},"103":{"xOffset":-1,"yOffset":3,"xAdvance":22,"rect":{"x":351,"y":160,"width":32,"height":43}},"104":{"xOffset":0,"yOffset":-6,"xAdvance":21,"rect":{"x":140,"y":160,"width":30,"height":44}},"105":{"xOffset":0,"yOffset":-4,"xAdvance":8,"rect":{"x":285,"y":340,"width":18,"height":42}},"106":{"xOffset":0,"yOffset":-5,"xAdvance":8,"rect":{"x":160,"y":56,"width":18,"height":51}},"107":{"xOffset":0,"yOffset":-6,"xAdvance":18,"rect":{"x":172,"y":160,"width":29,"height":44}},"108":{"xOffset":0,"yOffset":-6,"xAdvance":8,"rect":{"x":229,"y":160,"width":17,"height":44}},"109":{"xOffset":0,"yOffset":3,"xAdvance":33,"rect":{"x":2,"y":384,"width":42,"height":35}},"110":{"xOffset":0,"yOffset":3,"xAdvance":21,"rect":{"x":181,"y":384,"width":30,"height":35}},"111":{"xOffset":-1,"yOffset":3,"xAdvance":21,"rect":{"x":114,"y":384,"width":32,"height":35}},"112":{"xOffset":0,"yOffset":3,"xAdvance":22,"rect":{"x":385,"y":160,"width":32,"height":43}},"113":{"xOffset":-1,"yOffset":3,"xAdvance":22,"rect":{"x":2,"y":207,"width":32,"height":43}},"114":{"xOffset":0,"yOffset":3,"xAdvance":13,"rect":{"x":371,"y":384,"width":24,"height":35}},"115":{"xOffset":-1,"yOffset":3,"xAdvance":18,"rect":{"x":309,"y":384,"width":29,"height":35}},"116":{"xOffset":-2,"yOffset":-3,"xAdvance":10,"rect":{"x":324,"y":340,"width":23,"height":41}},"117":{"xOffset":0,"yOffset":3,"xAdvance":21,"rect":{"x":213,"y":384,"width":30,"height":35}},"118":{"xOffset":-2,"yOffset":3,"xAdvance":17,"rect":{"x":245,"y":384,"width":30,"height":35}},"119":{"xOffset":-2,"yOffset":3,"xAdvance":30,"rect":{"x":371,"y":340,"width":43,"height":35}},"120":{"xOffset":-2,"yOffset":3,"xAdvance":18,"rect":{"x":148,"y":384,"width":31,"height":35}},"121":{"xOffset":-1,"yOffset":3,"xAdvance":18,"rect":{"x":36,"y":207,"width":30,"height":43}},"122":{"xOffset":-1,"yOffset":3,"xAdvance":18,"rect":{"x":277,"y":384,"width":30,"height":35}},"123":{"xOffset":-2,"yOffset":-4,"xAdvance":10,"rect":{"x":394,"y":109,"width":24,"height":45}},"124":{"xOffset":1,"yOffset":-6,"xAdvance":9,"rect":{"x":248,"y":160,"width":17,"height":44}},"125":{"xOffset":-2,"yOffset":-4,"xAdvance":10,"rect":{"x":2,"y":160,"width":24,"height":45}},"126":{"xOffset":0,"yOffset":12,"xAdvance":24,"rect":{"x":286,"y":421,"width":32,"height":19}},"12289":{"xOffset":3,"yOffset":17,"xAdvance":40,"rect":{"x":194,"y":421,"width":25,"height":25}},"19978":{"xOffset":-1,"yOffset":-7,"xAdvance":40,"rect":{"x":108,"y":109,"width":52,"height":48}},"19979":{"xOffset":-1,"yOffset":-6,"xAdvance":40,"rect":{"x":162,"y":109,"width":51,"height":48}},"20214":{"xOffset":-2,"yOffset":-9,"xAdvance":40,"rect":{"x":163,"y":2,"width":52,"height":51}},"21457":{"xOffset":-1,"yOffset":-9,"xAdvance":40,"rect":{"x":109,"y":2,"width":52,"height":51}},"21697":{"xOffset":0,"yOffset":-7,"xAdvance":40,"rect":{"x":268,"y":109,"width":49,"height":48}},"22320":{"xOffset":-1,"yOffset":-8,"xAdvance":40,"rect":{"x":2,"y":109,"width":51,"height":49}},"22681":{"xOffset":-1,"yOffset":-9,"xAdvance":40,"rect":{"x":288,"y":56,"width":51,"height":50}},"22836":{"xOffset":0,"yOffset":-9,"xAdvance":40,"rect":{"x":55,"y":56,"width":51,"height":51}},"23376":{"xOffset":0,"yOffset":-7,"xAdvance":40,"rect":{"x":215,"y":109,"width":51,"height":48}},"24088":{"xOffset":0,"yOffset":-8,"xAdvance":40,"rect":{"x":108,"y":56,"width":50,"height":51}},"25670":{"xOffset":0,"yOffset":-8,"xAdvance":40,"rect":{"x":325,"y":2,"width":51,"height":51}},"26495":{"xOffset":-1,"yOffset":-8,"xAdvance":40,"rect":{"x":180,"y":56,"width":52,"height":50}},"26588":{"xOffset":-1,"yOffset":-9,"xAdvance":40,"rect":{"x":56,"y":2,"width":51,"height":52}},"27631":{"xOffset":-1,"yOffset":-8,"xAdvance":40,"rect":{"x":55,"y":109,"width":51,"height":49}},"27801":{"xOffset":-2,"yOffset":-9,"xAdvance":40,"rect":{"x":217,"y":2,"width":52,"height":51}},"29289":{"xOffset":0,"yOffset":-8,"xAdvance":40,"rect":{"x":341,"y":56,"width":50,"height":50}},"31383":{"xOffset":-1,"yOffset":-10,"xAdvance":40,"rect":{"x":2,"y":56,"width":51,"height":51}},"32440":{"xOffset":-1,"yOffset":-8,"xAdvance":40,"rect":{"x":234,"y":56,"width":52,"height":50}},"36523":{"xOffset":-1,"yOffset":-9,"xAdvance":40,"rect":{"x":271,"y":2,"width":52,"height":51}},"39280":{"xOffset":-1,"yOffset":-9,"xAdvance":40,"rect":{"x":2,"y":2,"width":52,"height":52}}},"kerningDict":{}}]],0,0,[0],[0],[0]],[[{"name":"skin-font","rect":[1550,456,414,470],"offset":[-4,2],"originalSize":[426,480],"rotated":1,"capInsets":[0,0,0,0]}],[0],0,[0],[1],[1]]]]