[1,0,0,[["cc.JsonAsset",["_name","json"],1]],[[0,0,1,3]],[[0,"skin",[{"unlock_diamonds":0,"skin_prefab":"Player1","id":1,"name":["无"],"value":[0],"key":[]},{"unlock_diamonds":500,"skin_prefab":"Player2","id":2,"name":["伤害"],"value":[0.1],"key":["atk"]},{"unlock_diamonds":500,"skin_prefab":"Player3","id":3,"name":["金币"],"value":[0.1],"key":["coin"]},{"unlock_diamonds":500,"skin_prefab":"Player4","id":4,"name":["生命"],"value":[0.1],"key":["hp"]},{"unlock_diamonds":500,"skin_prefab":"Player5","id":5,"name":["速度"],"value":[0.1],"key":["speed"]},{"unlock_diamonds":500,"skin_prefab":"Player6","id":6,"name":["射速"],"value":[0.1],"key":["fire_rate"]},{"unlock_diamonds":500,"skin_prefab":"Player7","id":7,"name":["生命","射速"],"value":[0.1,0.1],"key":["hp","speed"]}]]],0,0,[],[],[]]
