[1,["ecpdLyjvZBwrvm+cedCcQy","1a3443190","866GHysWhAhZ/Qv8SK8Bnm","3bcfkpZ4lHfLUkhDTqNBvW","48BiscQPhCWIcPlTTbxqPt","7efqt2psFN0bCxjF555B8v","b4Oj58KgpOzJsETgAMFkte","11f8a6f30","d6la7T7KxM+4CnxbzCx1Qi","70uq2wW1VO2IV9o6PZShZO","62RCzKhvhB375r6g5VeR5o","c45k4RjjxGV5I6daRiJN8Q","51jxPIhVxJBaY+hJq/oJfN","aemTe6CZ1KZ4/ZqW8IMGoJ","27EonJ7spC24F2YYqye10m","e4BZxdbNtMw7au+dR4SV8R","0bqS42L+FLhpAFIOjTNHDO","8dIY3PH1dCXaI7WveF8i8J","653xK63SlDb4M+B7jrJV37","a2MjXRFdtLlYQ5ouAFv/+R","1879Z6zXlBzrBT2ch9Ch1z","59u6DtmDBDsbLNwUyK2aBX","3fk65fxG1MjqHsCyV43kbN","15B2E+ac5K+aS5KX6ufK/o","edd6MWqBdJNJZ6GeZmVIe8","69MVhjB/5At5fO72LjeFer","83NNL2MEVIDZPklNce522R","1fYnm2ymJMd4OGclkEQsi2","bbS2+K+aNFYamdBePvXYOh","51sZU9qtxC66b0YuGjAokl","87BJgSHKVLOpnNJOct8W/S","d0CaC+VElGGqHV6xKLMCb0","ccwHcXjl5LkI/cA5MkBLUy","ecjrzlnyxBe4aaaoTSnTdb","39aLoNZuxGRaFkMj6rpsow"],["node","_spriteFrame","_parent","_textureSetter","_N$normalSprite","_N$pressedSprite","root","data"],[["cc.Node",["_name","_opacity","_active","_prefab","_contentSize","_components","_parent","_trs","_children","_color","_anchorPoint"],0,4,5,9,1,7,2,5,5],"cc.SpriteFrame",["cc.Label",["_string","_N$verticalAlign","_N$overflow","_fontSize","_lineHeight","_N$horizontalAlign","node","_materials"],-3,1,3],["cc.Sprite",["_sizeMode","_isTrimmedMode","_type","node","_materials","_spriteFrame"],0,1,3,6],["cc.Layout",["_resize","_N$layoutType","_N$spacingX","_N$paddingLeft","_N$paddingRight","_N$spacingY","node","_layoutSize"],-3,1,5],["cc.PrefabInfo",["fileId","root"],2,1],["cc.Button",["_N$transition","zoomScale","node","_N$normalSprite","_N$pressedSprite"],1,1,6,6],["cc.Widget",["_alignFlags","_top","node"],1,1],["cc.Prefab",["_name"],2],["cc.Node",["_name","_parent","_children","_components","_prefab","_contentSize","_trs"],2,1,12,9,4,5,7],["fcc74C4cIhNvbMvtOWT7yp4",["node"],3,1],["cc.BlockInputEvents",["node"],3,1],["cc.LabelOutline",["_width","node","_color"],2,1,5],["324d8bOs2JMtZ1MwskTEiKp",["node"],3,1],["b9886QzqYZGsqulf57BDo3/",["i18n_string","node"],2,1]],[[5,0,1,2],[3,3,4,5,1],[13,0,1],[12,0,1,2,2],[0,0,6,5,3,4,7,2],[0,0,6,8,5,3,4,7,2],[2,0,3,4,5,1,2,6,7,7],[14,0,1,2],[2,0,3,5,1,2,6,7,6],[0,0,6,5,3,9,4,7,2],[0,0,6,5,3,9,4,10,7,2],[3,0,1,3,4,5,3],[0,0,8,5,3,4,7,2],[6,0,2,3,4,2],[9,0,1,2,3,4,5,6,2],[4,0,1,3,4,2,6,7,6],[3,0,1,3,4,3],[6,1,0,2,3],[0,0,5,3,9,4,7,2],[0,0,6,3,4,7,2],[0,0,6,5,3,9,4,2],[0,0,5,3,4,7,2],[0,0,1,6,5,3,9,4,3],[0,0,6,8,5,3,4,2],[0,0,6,3,4,2],[0,0,6,8,3,2],[0,0,2,6,8,3,3],[4,0,1,5,6,7,4],[3,2,0,3,4,5,3],[3,0,3,4,5,2],[11,0,1],[8,0,2],[0,0,8,5,3,4,10,2],[0,0,8,5,3,4,10,7,2],[0,0,5,3,9,4,2],[0,0,6,8,5,3,4,10,7,2],[10,0,1],[5,1,1],[4,0,1,2,6,7,4],[2,0,4,5,1,2,6,7,6],[2,0,4,5,1,6,7,5],[2,0,3,1,2,6,7,5],[2,0,3,4,1,2,6,7,6],[7,0,2,2],[7,0,1,2,3]],[[[{"name":"Garbage_Kuang","rect":[1423,885,337,197],"offset":[0,0],"originalSize":[337,197],"capInsets":[0,0,0,0]}],[1],0,[0],[3],[1]],[[{"name":"icon_garbage_QiTa","rect":[567,184,47,31],"offset":[0,0],"originalSize":[47,31],"rotated":1,"capInsets":[0,0,0,0]}],[1],0,[0],[3],[7]],[[{"name":"icon_garbage_YouHai","rect":[501,528,43,36],"offset":[0,0],"originalSize":[43,36],"capInsets":[0,0,0,0]}],[1],0,[0],[3],[7]],[[[31,"RarbageStationPre"],[12,"RarbageStationPre",[-3,-4],[[36,-2]],[37,-1],[5,1080,2400],[540,1200,0,0,0,0,1,1,1,1]],[5,"DiBan",1,[-7,-8,-9,-10,-11,-12],[[28,1,0,-5,[204],205],[30,-6]],[0,"249/ObM5lHBZS+WzXCUMlB",1],[5,1050,2180],[0,-60,0,0,0,0,1,1,1,1]],[5,"shang",2,[-14,-15,-16,-17],[[15,1,1,5,5,30,-13,[5,960,370]]],[0,"9abfSBHz9FSLrPsVSsv2RV",1],[5,960,370],[0,852.047,0,0,0,0,1,1,1,1]],[12,"DuiHuan",[-20,-21,-22],[[1,-18,[75],76],[17,1.05,3,-19]],[0,"4e/+r9WuZBrLNZ3cV4Tl25",1],[5,207,88],[-40,-48.775,0,0,0,0,1,1,1,0]],[12,"Obtain",[-25,-26,-27],[[1,-23,[84],85],[13,2,-24,86,87]],[0,"12XdM3nwpLu4ExDJr77lN3",1],[5,189,119],[-103,0,0,0,0,0,1,1,1,1]],[12,"DuiHuan",[-30,-31,-32],[[1,-28,[113],114],[17,1.05,3,-29]],[0,"12V3A4iXBFMZAR8JESP444",1],[5,207,88],[-40,-48.775,0,0,0,0,1,1,1,0]],[12,"Obtain",[-35,-36,-37],[[1,-33,[122],123],[13,2,-34,124,125]],[0,"40DihwSyxPgIAZ+YTbU8Gh",1],[5,189,119],[-103,0,0,0,0,0,1,1,1,1]],[12,"DuiHuan",[-40,-41,-42],[[1,-38,[151],152],[17,1.05,3,-39]],[0,"9ab2N0DvlGgZlMwuAm61HD",1],[5,207,88],[-40,-48.775,0,0,0,0,1,1,1,0]],[12,"Obtain",[-45,-46,-47],[[1,-43,[160],161],[13,2,-44,162,163]],[0,"ccCSSXKhhGyaSenNQkQeXx",1],[5,189,119],[-103,0,0,0,0,0,1,1,1,1]],[18,"TITTLE",[[6,"垃圾站",60,70,1,1,2,-48,[2]],[3,3,-49,[4,4278321689]],[2,-50],[7,"rarbageStation.TITTLE",-51]],[0,"4aTP7XloRD0JPFLB16+mnf",1],[4,4292274418],[5,260,70],[0,-35,0,0,0,0,1,1,1,1]],[14,"children",3,[[[19,"Btn",-53,[0,"b6T9HpiYtLwIAS9obURHXa",1],[5,120,50],[0,89.451,0,0,0,0,1,1,1,1]],-54,-55],4,1,1],[[1,-52,[16],17]],[0,"68X0+B7npHt45hFTQDGGAc",1],[5,215,354],[-367.5,0,0,0,0,0,1,1,1,1]],[5,"Kuang",11,[-57,-58,-59],[[1,-56,[9],10]],[0,"329ndLen5PZbQKE1s5C3mp",1],[5,120,111],[0,-35.169,0,0,0,0,1,1,1,1]],[20,"TXT",12,[[6,"厨余垃圾",26,35,1,1,2,-60,[7]],[2,-61],[7,"rarbageStation.sort0",-62],[3,2,-63,[4,4278656816]]],[0,"48zC6JYdRAbKj0C4qi9DwT",1],[4,4291752703],[5,120,35]],[14,"children",3,[[[19,"Btn",-65,[0,"21QRFIcGhPqryo+UAU1nWK",1],[5,120,50],[0,89.451,0,0,0,0,1,1,1,1]],-66,-67],4,1,1],[[1,-64,[29],30]],[0,"8eQ3e4sRFI7pR6Z+eAMq2I",1],[5,215,354],[-122.5,0,0,0,0,0,1,1,1,1]],[5,"Kuang",14,[-69,-70,-71],[[1,-68,[22],23]],[0,"8fdcLN6xJItpWysIu0iNvX",1],[5,120,111],[0,-35.169,0,0,0,0,1,1,1,1]],[20,"TXT",15,[[6,"其他垃圾",26,35,1,1,2,-72,[20]],[2,-73],[7,"rarbageStation.sort1",-74],[3,2,-75,[4,4278656816]]],[0,"26O6oF/G5CnLpT+TPLGONx",1],[4,4291752703],[5,120,35]],[14,"children",3,[[[19,"Btn",-77,[0,"85Y582l0pJQLr62TKaIfjf",1],[5,120,50],[0,89.451,0,0,0,0,1,1,1,1]],-78,-79],4,1,1],[[1,-76,[42],43]],[0,"30KjH+4bFKPJczOoontdrG",1],[5,215,354],[122.5,0,0,0,0,0,1,1,1,1]],[5,"Kuang",17,[-81,-82,-83],[[1,-80,[35],36]],[0,"902H0P/xtI1bAP1Vcq9usz",1],[5,120,111],[0,-35.169,0,0,0,0,1,1,1,1]],[20,"TXT",18,[[6,"回收垃圾",26,35,1,1,2,-84,[33]],[2,-85],[7,"rarbageStation.sort2",-86],[3,2,-87,[4,4278656816]]],[0,"642E5njgZO968oRP77iX6H",1],[4,4291752703],[5,120,35]],[14,"children",3,[[[19,"Btn",-89,[0,"81EMu3D75Ero4p0uIWkLHg",1],[5,120,50],[0,89.451,0,0,0,0,1,1,1,1]],-90,-91],4,1,1],[[1,-88,[55],56]],[0,"b4Zb8aa4hCDq57JadYzQKi",1],[5,215,354],[367.5,0,0,0,0,0,1,1,1,1]],[5,"Kuang",20,[-93,-94,-95],[[1,-92,[48],49]],[0,"9aTUw6YSVFjZSKF4t70HRo",1],[5,120,111],[0,-35.169,0,0,0,0,1,1,1,1]],[20,"TXT",21,[[6,"有害垃圾",26,35,1,1,2,-96,[46]],[2,-97],[7,"rarbageStation.sort3",-98],[3,2,-99,[4,4278656816]]],[0,"83/N5tI4ZDILOCB+ST6BUg",1],[4,4291752703],[5,120,35]],[5,"zhong",2,[-101,-102,-103],[[38,1,1,15,-100,[5,1041,200]]],[0,"58npsX0FZHDosYkyGYXF6Z",1],[5,1041,200],[0,554.273,0,0,0,0,1,0.95,0.95,1]],[12,"node",[-105,-106,-107],[[15,1,1,10,10,15,-104,[5,302,90]]],[0,"21PLyhqE5KQI5xmoi7Gfyu",1],[5,302,90],[0,42.343,0,0,0,0,1,1,1,1]],[9,"TXT",4,[[8,"兑换",36,1,1,2,-108,[72]],[2,-109],[7,"rarbageStation.exchange",-110],[3,2,-111,[4,4278656816]]],[0,"fdOLF9wqRMl7dkLXqnnrzX",1],[4,4291752703],[5,90,40],[-49.752,0,0,0,0,0,1,1,1,1]],[4,"TXT",5,[[6,"立即获取",35,45,1,1,2,-112,[82]],[3,2,-113,[4,4278190080]],[2,-114],[7,"rarbageStation.offHand",-115]],[0,"5dWmDNIhlDvo0ryZcYXTHk",1],[5,150,45],[0,30,0,0,0,0,1,1,1,1]],[21,"TXT",[[6,"立即获取",35,45,1,1,2,-116,[88]],[3,2,-117,[4,4278190080]],[2,-118],[7,"rarbageStation.offHand",-119]],[0,"cbcaUPCS5GjL/xzqHHuX0+",1],[5,150,45],[0,30,0,0,0,0,1,1,1,1]],[12,"node",[-121,-122,-123],[[15,1,1,10,10,15,-120,[5,302,90]]],[0,"28rHjWdxBEF5Bm7bVyFqz6",1],[5,302,90],[0,42.343,0,0,0,0,1,1,1,1]],[9,"TXT",6,[[8,"兑换",36,1,1,2,-124,[110]],[2,-125],[7,"rarbageStation.exchange",-126],[3,2,-127,[4,4278656816]]],[0,"b6vzzy1JtJFbWamnIrlPWT",1],[4,4291752703],[5,90,40],[-49.752,0,0,0,0,0,1,1,1,1]],[4,"TXT",7,[[6,"立即获取",35,45,1,1,2,-128,[120]],[3,2,-129,[4,4278190080]],[2,-130],[7,"rarbageStation.offHand",-131]],[0,"137WBoHfBDtY59NNpE0LXV",1],[5,150,45],[0,30,0,0,0,0,1,1,1,1]],[21,"TXT",[[6,"立即获取",35,45,1,1,2,-132,[126]],[3,2,-133,[4,4278190080]],[2,-134],[7,"rarbageStation.offHand",-135]],[0,"1essyBMZ5E57n43WcKS6Bl",1],[5,150,45],[0,30,0,0,0,0,1,1,1,1]],[12,"node",[-137,-138,-139],[[15,1,1,10,10,15,-136,[5,302,90]]],[0,"73fFi1ssdJyIv8wKE+GTGa",1],[5,302,90],[0,42.343,0,0,0,0,1,1,1,1]],[9,"TXT",8,[[8,"兑换",36,1,1,2,-140,[148]],[2,-141],[7,"rarbageStation.exchange",-142],[3,2,-143,[4,4278656816]]],[0,"39KRQp3zdBQbxzhZuNDxd2",1],[4,4291752703],[5,90,40],[-49.752,0,0,0,0,0,1,1,1,1]],[4,"TXT",9,[[6,"立即获取",35,45,1,1,2,-144,[158]],[3,2,-145,[4,4278190080]],[2,-146],[7,"rarbageStation.offHand",-147]],[0,"8365W8gBtHzYcgBk5XlFrf",1],[5,150,45],[0,30,0,0,0,0,1,1,1,1]],[21,"TXT",[[6,"立即获取",35,45,1,1,2,-148,[164]],[3,2,-149,[4,4278190080]],[2,-150],[7,"rarbageStation.offHand",-151]],[0,"87IW6ewwhBM4b3YSMJcXhs",1],[5,150,45],[0,30,0,0,0,0,1,1,1,1]],[32,"xiao",[-153,-154,-155],[[27,1,3,2,-152,[5,992,124]]],[0,"37nWcSg9lE/KTCSj7VE6VR",1],[5,992,124],[0,0.5,1]],[14,"Children",36,[[-157,[24,"Btn",-158,[0,"d2mxYp24NLHb5A6FaDlCEa",1],[5,110,110]],-159],1,4,1],[[1,-156,[174],175]],[0,"3aRB5Zb4BJD5FTxLfcN6hc",1],[5,124,124],[-434,-62,0,0,0,0,1,1,1,1]],[14,"Children",36,[[-161,[24,"Btn",-162,[0,"76hVu/SNxAsKUwVgfbhc8y",1],[5,110,110]],-163],1,4,1],[[1,-160,[179],180]],[0,"d6xSaibjJGjLNb686x6fpL",1],[5,124,124],[-310,-62,0,0,0,0,1,1,1,1]],[14,"Children",36,[[-165,[24,"Btn",-166,[0,"24DO5zfA5MI6URr3A9zgn3",1],[5,110,110]],-167],1,4,1],[[1,-164,[184],185]],[0,"ccJVFAqkdGbaouCxOlIsNl",1],[5,124,124],[-186,-62,0,0,0,0,1,1,1,1]],[5,"ShuoMing",2,[-169,-170,-171],[[29,0,-168,[198],199]],[0,"75zBo6Mx9NZL0p2sSmKtTh",1],[5,1050,134],[0,-1060,0,0,0,0,1,1,1,1]],[21,"TXT",[[39,"升级",50,1,1,2,-172,[191]],[2,-173],[7,"upgrade",-174],[3,2,-175,[4,4278190080]]],[0,"c4ZScK4pFI+bFi8Mc2Rwi9",1],[5,150,50],[0,3,0,0,0,0,1,1,1,1]],[22,"CloseBtnMask",99.96000000000001,1,[[43,45,-176],[30,-177],[29,0,-178,[0],1]],[0,"f9D9PZSt5N1b++v3PC8wZf",1],[4,4278190080],[5,1080,2400]],[5,"public_Tittle",2,[10],[[1,-179,[3],4],[44,17,-151.21100000000013,-180]],[0,"67PLL0qj1MlbcjA1JauE+y",1],[5,309,194],[0,1144.2110000000002,0,0,0,0,1,1,1,1]],[9,"NUM",12,[[6,"容量:12/18",25,35,1,1,2,-181,[8]],[2,-182],[3,2,-183,[4,4278190080]]],[0,"9cGt/wSLJDIbXvtNwjZox3",1],[4,4284254207],[5,110,35],[0,-30,0,0,0,0,1,1,1,1]],[5,"cost",11,[-185,-186],[[1,-184,[14],15]],[0,"0dcTiEM3ZFZZ47S4w8r2Hy",1],[5,138,51],[0,-131.213,0,0,0,0,1,1,1,1]],[9,"Price",45,[[6,"99,999",25,35,1,1,2,-187,[13]],[2,-188],[3,2,-189,[4,4278190080]]],[0,"7f6Ci9e+JGKqTJxUCZW00o",1],[4,4286961919],[5,90,35],[16.786,5,0,0,0,0,1,1,1,1]],[9,"NUM",15,[[6,"容量:12/18",25,35,1,1,2,-190,[21]],[2,-191],[3,2,-192,[4,4278190080]]],[0,"738YdcUJpEwpzzgJRG6fMK",1],[4,4284254207],[5,110,35],[0,-30,0,0,0,0,1,1,1,1]],[5,"cost",14,[-194,-195],[[1,-193,[27],28]],[0,"ceOvoTRPBFWqV/LQECTawP",1],[5,138,51],[0,-131.213,0,0,0,0,1,1,1,1]],[9,"Price",48,[[6,"99,999",25,35,1,1,2,-196,[26]],[2,-197],[3,2,-198,[4,4278190080]]],[0,"63uoLA7LRBOoYH83g1z3R2",1],[4,4286961919],[5,90,35],[16.786,5,0,0,0,0,1,1,1,1]],[9,"NUM",18,[[6,"容量:12/18",25,35,1,1,2,-199,[34]],[2,-200],[3,2,-201,[4,4278190080]]],[0,"4cyWnUwRFP55VeHNQ0zL3x",1],[4,4284254207],[5,110,35],[0,-30,0,0,0,0,1,1,1,1]],[5,"cost",17,[-203,-204],[[1,-202,[40],41]],[0,"b67nHfISFAnY2zQWVi+q9w",1],[5,138,51],[0,-131.213,0,0,0,0,1,1,1,1]],[9,"Price",51,[[6,"99,999",25,35,1,1,2,-205,[39]],[2,-206],[3,2,-207,[4,4278190080]]],[0,"08n4Dvfg1BnbKPKAQanHya",1],[4,4286961919],[5,90,35],[16.786,5,0,0,0,0,1,1,1,1]],[9,"NUM",21,[[6,"容量:12/18",25,35,1,1,2,-208,[47]],[2,-209],[3,2,-210,[4,4278190080]]],[0,"e8bM66B9JGgIPN+ehtOrDZ",1],[4,4284254207],[5,110,35],[0,-30,0,0,0,0,1,1,1,1]],[5,"cost",20,[-212,-213],[[1,-211,[53],54]],[0,"4flGjaetRFgY8a6NhHZ/CX",1],[5,138,51],[0,-131.213,0,0,0,0,1,1,1,1]],[9,"Price",54,[[6,"99,999",25,35,1,1,2,-214,[52]],[2,-215],[3,2,-216,[4,4278190080]]],[0,"d1VE4YiJ1AIYhDR3W7Szy9",1],[4,4286961919],[5,90,35],[16.786,5,0,0,0,0,1,1,1,1]],[5,"children",23,[-218,-219],[[1,-217,[93],94]],[0,"0b2BRjXpZCp4lpiu5rA17J",1],[5,337,197],[-352,0,0,0,0,0,1,1,1,1]],[25,"state0",56,[24,4,-220],[0,"30iCG7WPhJu7jjv0ua2OFj",1]],[5,"item",24,[-222,-223],[[1,-221,[60],61]],[0,"19Fj73YilJto1KhNaEq5jO",1],[5,84,83],[-99,0,0,0,0,0,1,1,1,1]],[10,"num",58,[[8,"x50",30,2,1,2,-224,[59]],[2,-225],[3,2,-226,[4,4278190080]]],[0,"a1GmbfoEtAaYn8Zh0jzI9t",1],[4,4284996751],[5,80,40],[0,1,0.5],[37.473,-25.694,0,0,0,0,1,1,1,1]],[23,"item",24,[-228,-229],[[1,-227,[65],66]],[0,"21Pzd3nAxOpZ1dHPd5TlxT",1],[5,84,83]],[10,"num",60,[[8,"x50",30,2,1,2,-230,[64]],[2,-231],[3,2,-232,[4,4278190080]]],[0,"f9ZEC4UnJELIRQixdd+QWx",1],[4,4278220287],[5,80,40],[0,1,0.5],[37.473,-25.694,0,0,0,0,1,1,1,1]],[5,"item",24,[-234,-235],[[1,-233,[70],71]],[0,"7fCq8bgCxDipFZlzI29+cf",1],[5,84,83],[99,0,0,0,0,0,1,1,1,1]],[10,"num",62,[[8,"x50",30,2,1,2,-236,[69]],[2,-237],[3,2,-238,[4,4278190080]]],[0,"f3GlL+di9JJ669FJ4X5I+j",1],[4,4284996751],[5,80,40],[0,1,0.5],[37.473,-25.694,0,0,0,0,1,1,1,1]],[10,"num",4,[[8,"x3",30,2,1,2,-239,[74]],[2,-240],[3,2,-241,[4,4278190080]]],[0,"fbj2dm7SBM+qNJO0khc600",1],[4,4286961919],[5,80,40],[0,1,0.5],[94.756,-18.627,0,0,0,0,1,1,1,1]],[18,"TXT",[[6,"2级垃圾站解锁",35,45,1,1,2,-242,[79]],[3,2,-243,[4,4278190080]],[2,-244]],[0,"a72+jOz2xMoYBk1qDcJs13",1],[4,4284996751],[5,300,50],[0,56.068,0,0,0,0,1,1,1,1]],[12,"node",[5,-246],[[15,1,1,10,10,20,-245,[5,415,140]]],[0,"9ev7mhxOJFHopZ9rNgOodO",1],[5,415,140],[0,-37.23,0,0,0,0,1,0.75,0.75,0.814]],[9,"Num",5,[[6,"5",35,45,1,1,2,-247,[83]],[3,2,-248,[4,4278190080]],[2,-249]],[0,"c1QyYtDf9IOpd7PLn19Rey",1],[4,4286961919],[5,50,45],[20.642,-28.281,0,0,0,0,1,1,1,1]],[5,"ObtainVideo",66,[27],[[1,-250,[89],90],[13,2,-251,91,92]],[0,"3eDmWHkSpDPKr4HQBZyALx",1],[5,186,119],[104.5,0,0,0,0,0,1,1,1,1]],[23,"children",23,[-253,-254],[[1,-252,[131],132]],[0,"34jShT+bJMgZHosaoWJ7Kp",1],[5,337,197]],[25,"state0",69,[28,6,-255],[0,"f4ZJCV/DhN2qnHRmrjPcrE",1]],[5,"item",28,[-257,-258],[[1,-256,[98],99]],[0,"7aiApgCaBNVK+fgtSa6iHx",1],[5,84,83],[-99,0,0,0,0,0,1,1,1,1]],[10,"num",71,[[8,"x50",30,2,1,2,-259,[97]],[2,-260],[3,2,-261,[4,4278190080]]],[0,"dd+ZYO9xlHPbPCryq0KyB8",1],[4,4284996751],[5,80,40],[0,1,0.5],[37.473,-25.694,0,0,0,0,1,1,1,1]],[23,"item",28,[-263,-264],[[1,-262,[103],104]],[0,"2fwP12msVIRI1A5ZKW7hEM",1],[5,84,83]],[10,"num",73,[[8,"x50",30,2,1,2,-265,[102]],[2,-266],[3,2,-267,[4,4278190080]]],[0,"2ehCIFH3lFWbF2/CDx5pb0",1],[4,4278220287],[5,80,40],[0,1,0.5],[37.473,-25.694,0,0,0,0,1,1,1,1]],[5,"item",28,[-269,-270],[[1,-268,[108],109]],[0,"4f+ef9UVFLS6qypdQDEdg3",1],[5,84,83],[99,0,0,0,0,0,1,1,1,1]],[10,"num",75,[[8,"x50",30,2,1,2,-271,[107]],[2,-272],[3,2,-273,[4,4278190080]]],[0,"b0Ujlru7pMiL7Jr4PWx0b1",1],[4,4284996751],[5,80,40],[0,1,0.5],[37.473,-25.694,0,0,0,0,1,1,1,1]],[10,"num",6,[[8,"x3",30,2,1,2,-274,[112]],[2,-275],[3,2,-276,[4,4278190080]]],[0,"08EhaKiH9DrZ/4ekweihdM",1],[4,4286961919],[5,80,40],[0,1,0.5],[94.756,-18.627,0,0,0,0,1,1,1,1]],[18,"TXT",[[6,"2级垃圾站解锁",35,45,1,1,2,-277,[117]],[3,2,-278,[4,4278190080]],[2,-279]],[0,"94cUGFqPBAaIGv1xGVfip1",1],[4,4284996751],[5,300,50],[0,56.068,0,0,0,0,1,1,1,1]],[12,"node",[7,-281],[[15,1,1,10,10,20,-280,[5,415,140]]],[0,"43rpLwU5dPrJtEgN2sRp3X",1],[5,415,140],[0,-37.23,0,0,0,0,1,0.75,0.75,0.814]],[9,"Num",7,[[6,"5",35,45,1,1,2,-282,[121]],[3,2,-283,[4,4278190080]],[2,-284]],[0,"f30BsfWttKobDGAtC5zh4r",1],[4,4286961919],[5,50,45],[20.642,-28.281,0,0,0,0,1,1,1,1]],[5,"ObtainVideo",79,[31],[[1,-285,[127],128],[13,2,-286,129,130]],[0,"deuzd3k0dH4pdzJCKeq4pK",1],[5,186,119],[104.5,0,0,0,0,0,1,1,1,1]],[5,"children",23,[-288,-289],[[1,-287,[169],170]],[0,"82QJgiWYFOPqtfi6/NUsgz",1],[5,337,197],[352,0,0,0,0,0,1,1,1,1]],[25,"state0",82,[32,8,-290],[0,"42bVhE+A5KdqipczzPDqj2",1]],[5,"item",32,[-292,-293],[[1,-291,[136],137]],[0,"7bU1KcCrpDNan7tRWDOoIE",1],[5,84,83],[-99,0,0,0,0,0,1,1,1,1]],[10,"num",84,[[8,"x50",30,2,1,2,-294,[135]],[2,-295],[3,2,-296,[4,4278190080]]],[0,"45Ue0UsaZBFIiGXi8vIqJA",1],[4,4284996751],[5,80,40],[0,1,0.5],[37.473,-25.694,0,0,0,0,1,1,1,1]],[23,"item",32,[-298,-299],[[1,-297,[141],142]],[0,"14JyaCxAxFK6xnrvazTRlT",1],[5,84,83]],[10,"num",86,[[8,"x50",30,2,1,2,-300,[140]],[2,-301],[3,2,-302,[4,4278190080]]],[0,"93B/Xq/cVKz6dLK3Qixe9c",1],[4,4278220287],[5,80,40],[0,1,0.5],[37.473,-25.694,0,0,0,0,1,1,1,1]],[5,"item",32,[-304,-305],[[1,-303,[146],147]],[0,"3dDFeJAxlHoo2yp/jQtwmP",1],[5,84,83],[99,0,0,0,0,0,1,1,1,1]],[10,"num",88,[[8,"x50",30,2,1,2,-306,[145]],[2,-307],[3,2,-308,[4,4278190080]]],[0,"83szfeNYlBWZ5y3+pkxbGC",1],[4,4284996751],[5,80,40],[0,1,0.5],[37.473,-25.694,0,0,0,0,1,1,1,1]],[10,"num",8,[[8,"x3",30,2,1,2,-309,[150]],[2,-310],[3,2,-311,[4,4278190080]]],[0,"b4dZjGfJdHeZbTNt5fIXeh",1],[4,4286961919],[5,80,40],[0,1,0.5],[94.756,-18.627,0,0,0,0,1,1,1,1]],[18,"TXT",[[6,"2级垃圾站解锁",35,45,1,1,2,-312,[155]],[3,2,-313,[4,4278190080]],[2,-314]],[0,"42FnA8WCBNYJm6Fm/h5kgI",1],[4,4284996751],[5,300,50],[0,56.068,0,0,0,0,1,1,1,1]],[12,"node",[9,-316],[[15,1,1,10,10,20,-315,[5,415,140]]],[0,"89/a78fOdJtpOkTll1jex3",1],[5,415,140],[0,-37.23,0,0,0,0,1,0.75,0.75,0.814]],[9,"Num",9,[[6,"5",35,45,1,1,2,-317,[159]],[3,2,-318,[4,4278190080]],[2,-319]],[0,"b1koqp9bBMr4L868Hy2SJU",1],[4,4286961919],[5,50,45],[20.642,-28.281,0,0,0,0,1,1,1,1]],[5,"ObtainVideo",92,[35],[[1,-320,[165],166],[13,2,-321,167,168]],[0,"fbTT2W9OdKa5eqZYW6KgxK",1],[5,186,119],[104.5,0,0,0,0,0,1,1,1,1]],[33,"Out",[36,-323],[[27,1,2,5,-322,[5,992,255]]],[0,"df/cd3FkNPWIx8CP8safqw",1],[5,992,255],[0,0.5,1],[0,694.982,0,0,0,0,1,1,1,1]],[34,"Tips",[[40,"2级垃圾站解锁",50,1,1,-324,[186]],[3,2,-325,[4,4278190080]],[2,-326]],[0,"43YSvAAXdO66UiYKdQf6qO",1],[4,4286961919],[5,266.25,67]],[5,"UpBtn",40,[41],[[11,2,false,-327,[192],193],[13,2,-328,194,195]],[0,"74slT21dtEYZJpdGCFm6Ub",1],[5,188,108],[370,0,0,0,0,0,1,1,1,0]],[10,"Level_",40,[[41,"垃圾站等级:1",35,1,2,-329,[196]],[2,-330],[3,2,-331,[4,4278656816]]],[0,"e9EZmUBp9Pn7BYQWRXUCFS",1],[4,4291752703],[5,220,45],[0,0,0.5],[-476.768,28.311,0,0,0,0,1,1,1,1]],[10,"UpTips",40,[[42,"连续点击两个相同的物品可将其放入对应的垃圾箱中",35,45,1,2,-332,[197]],[2,-333],[7,"rarbageStation.Tips",-334]],[0,"68gnMSm9hOJraMJCGk4OuL",1],[4,4280308333],[5,700,45],[0,0,0.5],[-476.768,-25,0,0,0,0,1,1,1,1]],[4,"ShanChu",57,[[1,-335,[77],78],[17,1.05,3,-336]],[0,"4cmgH/XF5L1Lq8UlT89vmd",1],[5,71,62],[129.887,-65.321,0,0,0,0,1,1,1,0]],[26,"state1",false,56,[65,66],[0,"2b46lrqG5IHq+39T3pEKEU",1]],[4,"ShanChu",70,[[1,-337,[115],116],[17,1.05,3,-338]],[0,"fdApIx4N1Hybmeu4S+Q474",1],[5,71,62],[129.887,-65.321,0,0,0,0,1,1,1,0]],[26,"state1",false,69,[78,79],[0,"97JUwC5oBGWYwgiDpeQgAi",1]],[4,"ShanChu",83,[[1,-339,[153],154],[17,1.05,3,-340]],[0,"88wv41d9hLta2nfCGRqIVB",1],[5,71,62],[129.887,-65.321,0,0,0,0,1,1,1,0]],[26,"state1",false,82,[91,92],[0,"b8RA8mVz1Hy6uTSxmt2UDx",1]],[5,"Xia",2,[95],[[28,1,0,-341,[189],190]],[0,"a9cVZoEfNDyoFDnvtPVCnD",1],[5,1050,1440],[0,-273.39,0,0,0,0,1,1,1,1]],[35,"Da",95,[-343],[[27,1,2,1,-342,[5,992,126]]],[0,"31fDNuFvtBG6GTP4mJ2onO",1],[5,992,126],[0,0.5,1],[0,-129,0,0,0,0,1,1,1,1]],[5,"Children",107,[96],[[1,-344,[187],188]],[0,"72JpF8vatKcaFWBBV/hE9T",1],[5,1006,126],[0,-63,0,0,0,0,1,1,1,1]],[4,"CloseBtn",2,[[1,-345,[200],201],[13,2,-346,202,203]],[0,"d4zacAZyZJxZHCNC7OjcPm",1],[5,111,111],[484.313,1105.622,0,0,0,0,1,1,1,1]],[4,"icon",12,[[11,2,false,-347,[5],6]],[0,"d0E7OPM2NGQ7VjXe7xC47v",1],[5,47,37],[0,30,0,0,0,0,1,1,1,1]],[4,"cash",45,[[1,-348,[11],12]],[0,"a866ubCHZOLaFz4cLC4Mdl",1],[5,45,38],[-47,0,0,0,0,0,1,0.7,0.7,1]],[4,"icon",15,[[11,2,false,-349,[18],19]],[0,"d07rIz7a1Ng5dsOGyOBPuq",1],[5,47,31],[0,30,0,0,0,0,1,1,1,1]],[4,"cash",48,[[1,-350,[24],25]],[0,"a7mtLDBEFBiJOAW9toL9GC",1],[5,45,38],[-47,0,0,0,0,0,1,0.7,0.7,0.7]],[4,"icon",18,[[11,2,false,-351,[31],32]],[0,"7a41gm+uhCPb8pVwjItd3/",1],[5,52,36],[0,30,0,0,0,0,1,1,1,1]],[4,"cash",51,[[1,-352,[37],38]],[0,"2cCN/ouA5HCqgKIEpSm8Fe",1],[5,45,38],[-47,0,0,0,0,0,1,0.7,0.7,0.7]],[4,"icon",21,[[11,2,false,-353,[44],45]],[0,"capr0zRXVHlYeii+I9KOJq",1],[5,43,36],[0,30,0,0,0,0,1,1,1,1]],[4,"cash",54,[[1,-354,[50],51]],[0,"20jk9RcWZPk7DuLbv0MV4U",1],[5,45,38],[-47,0,0,0,0,0,1,0.7,0.7,0.7]],[4,"icon",58,[[11,2,false,-355,[57],58]],[0,"4cla5NEqpJ1qjb+Z43Jd6Z",1],[5,160,160],[0,0,0,0,0,0,1,0.4,0.4,1]],[4,"icon",60,[[11,2,false,-356,[62],63]],[0,"b2uFvsWaZLvJhOiL+XDu2G",1],[5,160,160],[0,0,0,0,0,0,1,0.4,0.4,1]],[4,"icon",62,[[11,2,false,-357,[67],68]],[0,"2cQgKADOpFQ6yeB/gW8HB6",1],[5,160,160],[0,0,0,0,0,0,1,0.4,0.4,1]],[4,"icon",4,[[16,2,false,-358,[73]]],[0,"62boatraRCS6jJX6ESVObY",1],[5,160,160],[49.753,0,0,0,0,0,1,0.5,0.5,1]],[4,"icon_gem",5,[[1,-359,[80],81]],[0,"7baXeZ53VFJYkHIvli9d2s",1],[5,36,34],[-45.919,-31.416,0,0,0,0,1,1,1,1]],[4,"icon",71,[[11,2,false,-360,[95],96]],[0,"52knTFbVFN/o97qilYTdXX",1],[5,160,160],[0,0,0,0,0,0,1,0.4,0.4,1]],[4,"icon",73,[[11,2,false,-361,[100],101]],[0,"efvdMCyVtBhK7hN9WY8J2Y",1],[5,160,160],[0,0,0,0,0,0,1,0.4,0.4,1]],[4,"icon",75,[[11,2,false,-362,[105],106]],[0,"1fvhm0OPFH+oNAKh8Lhota",1],[5,160,160],[0,0,0,0,0,0,1,0.4,0.4,1]],[4,"icon",6,[[16,2,false,-363,[111]]],[0,"15HPSFnQpL8KwSwlpwx4EM",1],[5,160,160],[49.753,0,0,0,0,0,1,0.5,0.5,1]],[4,"icon_gem",7,[[1,-364,[118],119]],[0,"db0OH7KeVPXozsH5iuNK1B",1],[5,36,34],[-45.919,-31.416,0,0,0,0,1,1,1,1]],[4,"icon",84,[[11,2,false,-365,[133],134]],[0,"157XTCr5RIxoEyDbcHNPV7",1],[5,160,160],[0,0,0,0,0,0,1,0.4,0.4,1]],[4,"icon",86,[[11,2,false,-366,[138],139]],[0,"47oL6hFH5I3Z+rCuxonEyc",1],[5,160,160],[0,0,0,0,0,0,1,0.4,0.4,1]],[4,"icon",88,[[11,2,false,-367,[143],144]],[0,"22sJFWrnBL6K7HjPcOE1Sd",1],[5,160,160],[0,0,0,0,0,0,1,0.4,0.4,1]],[4,"icon",8,[[16,2,false,-368,[149]]],[0,"a0RT8Rkc1JNJ7ztLHg2WcN",1],[5,160,160],[49.753,0,0,0,0,0,1,0.5,0.5,1]],[4,"icon_gem",9,[[1,-369,[156],157]],[0,"d8t5nXNLBLTLDKHGPbfylO",1],[5,36,34],[-45.919,-31.416,0,0,0,0,1,1,1,1]],[22,"Guang",125,37,[[1,-370,[171],172]],[0,"5cugf53RtGWajc0kGOpQmr",1],[4,4278255360],[5,124,124]],[4,"icon",37,[[16,2,false,-371,[173]]],[0,"06hUaxkEJNJbRIcvWZ3v3g",1],[5,160,160],[0,0,0,0,0,0,1,0.7,0.7,1]],[22,"Guang",125,38,[[1,-372,[176],177]],[0,"a5o3jRf7xErrVWyvAMIkCb",1],[4,4278255360],[5,124,124]],[4,"icon",38,[[16,2,false,-373,[178]]],[0,"6513n3eWBP15Xd/Rb2JgFG",1],[5,160,160],[0,0,0,0,0,0,1,0.7,0.7,1]],[22,"Guang",125,39,[[1,-374,[181],182]],[0,"d8XfGVerhAv7/bF2riSE/G",1],[4,4278255360],[5,124,124]],[4,"icon",39,[[16,2,false,-375,[183]]],[0,"cf3wwGjWdHpLBqPuQnDdck",1],[5,160,160],[0,0,0,0,0,0,1,0.7,0.7,1]]],0,[0,6,1,0,0,1,0,-1,42,0,-2,2,0,0,2,0,0,2,0,-1,43,0,-2,3,0,-3,23,0,-4,106,0,-5,40,0,-6,109,0,0,3,0,-1,11,0,-2,14,0,-3,17,0,-4,20,0,0,4,0,0,4,0,-1,25,0,-2,121,0,-3,64,0,0,5,0,0,5,0,-1,122,0,-2,26,0,-3,67,0,0,6,0,0,6,0,-1,29,0,-2,126,0,-3,77,0,0,7,0,0,7,0,-1,127,0,-2,30,0,-3,80,0,0,8,0,0,8,0,-1,33,0,-2,131,0,-3,90,0,0,9,0,0,9,0,-1,132,0,-2,34,0,-3,93,0,0,10,0,0,10,0,0,10,0,0,10,0,0,11,0,2,11,0,-2,12,0,-3,45,0,0,12,0,-1,110,0,-2,13,0,-3,44,0,0,13,0,0,13,0,0,13,0,0,13,0,0,14,0,2,14,0,-2,15,0,-3,48,0,0,15,0,-1,112,0,-2,16,0,-3,47,0,0,16,0,0,16,0,0,16,0,0,16,0,0,17,0,2,17,0,-2,18,0,-3,51,0,0,18,0,-1,114,0,-2,19,0,-3,50,0,0,19,0,0,19,0,0,19,0,0,19,0,0,20,0,2,20,0,-2,21,0,-3,54,0,0,21,0,-1,116,0,-2,22,0,-3,53,0,0,22,0,0,22,0,0,22,0,0,22,0,0,23,0,-1,56,0,-2,69,0,-3,82,0,0,24,0,-1,58,0,-2,60,0,-3,62,0,0,25,0,0,25,0,0,25,0,0,25,0,0,26,0,0,26,0,0,26,0,0,26,0,0,27,0,0,27,0,0,27,0,0,27,0,0,28,0,-1,71,0,-2,73,0,-3,75,0,0,29,0,0,29,0,0,29,0,0,29,0,0,30,0,0,30,0,0,30,0,0,30,0,0,31,0,0,31,0,0,31,0,0,31,0,0,32,0,-1,84,0,-2,86,0,-3,88,0,0,33,0,0,33,0,0,33,0,0,33,0,0,34,0,0,34,0,0,34,0,0,34,0,0,35,0,0,35,0,0,35,0,0,35,0,0,36,0,-1,37,0,-2,38,0,-3,39,0,0,37,0,-1,133,0,2,37,0,-3,134,0,0,38,0,-1,135,0,2,38,0,-3,136,0,0,39,0,-1,137,0,2,39,0,-3,138,0,0,40,0,-1,97,0,-2,98,0,-3,99,0,0,41,0,0,41,0,0,41,0,0,41,0,0,42,0,0,42,0,0,42,0,0,43,0,0,43,0,0,44,0,0,44,0,0,44,0,0,45,0,-1,111,0,-2,46,0,0,46,0,0,46,0,0,46,0,0,47,0,0,47,0,0,47,0,0,48,0,-1,113,0,-2,49,0,0,49,0,0,49,0,0,49,0,0,50,0,0,50,0,0,50,0,0,51,0,-1,115,0,-2,52,0,0,52,0,0,52,0,0,52,0,0,53,0,0,53,0,0,53,0,0,54,0,-1,117,0,-2,55,0,0,55,0,0,55,0,0,55,0,0,56,0,-1,57,0,-2,101,0,-3,100,0,0,58,0,-1,118,0,-2,59,0,0,59,0,0,59,0,0,59,0,0,60,0,-1,119,0,-2,61,0,0,61,0,0,61,0,0,61,0,0,62,0,-1,120,0,-2,63,0,0,63,0,0,63,0,0,63,0,0,64,0,0,64,0,0,64,0,0,65,0,0,65,0,0,65,0,0,66,0,-2,68,0,0,67,0,0,67,0,0,67,0,0,68,0,0,68,0,0,69,0,-1,70,0,-2,103,0,-3,102,0,0,71,0,-1,123,0,-2,72,0,0,72,0,0,72,0,0,72,0,0,73,0,-1,124,0,-2,74,0,0,74,0,0,74,0,0,74,0,0,75,0,-1,125,0,-2,76,0,0,76,0,0,76,0,0,76,0,0,77,0,0,77,0,0,77,0,0,78,0,0,78,0,0,78,0,0,79,0,-2,81,0,0,80,0,0,80,0,0,80,0,0,81,0,0,81,0,0,82,0,-1,83,0,-2,105,0,-3,104,0,0,84,0,-1,128,0,-2,85,0,0,85,0,0,85,0,0,85,0,0,86,0,-1,129,0,-2,87,0,0,87,0,0,87,0,0,87,0,0,88,0,-1,130,0,-2,89,0,0,89,0,0,89,0,0,89,0,0,90,0,0,90,0,0,90,0,0,91,0,0,91,0,0,91,0,0,92,0,-2,94,0,0,93,0,0,93,0,0,93,0,0,94,0,0,94,0,0,95,0,-2,107,0,0,96,0,0,96,0,0,96,0,0,97,0,0,97,0,0,98,0,0,98,0,0,98,0,0,99,0,0,99,0,0,99,0,0,100,0,0,100,0,0,102,0,0,102,0,0,104,0,0,104,0,0,106,0,0,107,0,-1,108,0,0,108,0,0,109,0,0,109,0,0,110,0,0,111,0,0,112,0,0,113,0,0,114,0,0,115,0,0,116,0,0,117,0,0,118,0,0,119,0,0,120,0,0,121,0,0,122,0,0,123,0,0,124,0,0,125,0,0,126,0,0,127,0,0,128,0,0,129,0,0,130,0,0,131,0,0,132,0,0,133,0,0,134,0,0,135,0,0,136,0,0,137,0,0,138,0,7,1,4,2,57,5,2,66,6,2,70,7,2,79,8,2,83,9,2,92,10,2,43,24,2,57,27,2,68,28,2,70,31,2,81,32,2,83,35,2,94,36,2,95,41,2,97,65,2,101,66,2,101,78,2,103,79,2,103,91,2,105,92,2,105,95,2,106,96,2,108,375],[0,0,0,0,0,0,0,0,0,0,0,0,0,0,0,0,0,0,0,0,0,0,0,0,0,0,0,0,0,0,0,0,0,0,0,0,0,0,0,0,0,0,0,0,0,0,0,0,0,0,0,0,0,0,0,0,0,0,0,0,0,0,0,0,0,0,0,0,0,0,0,0,0,0,0,0,0,0,0,0,0,0,0,0,0,0,0,0,0,0,0,0,0,0,0,0,0,0,0,0,0,0,0,0,0,0,0,0,0,0,0,0,0,0,0,0,0,0,0,0,0,0,0,0,0,0,0,0,0,0,0,0,0,0,0,0,0,0,0,0,0,0,0,0,0,0,0,0,0,0,0,0,0,0,0,0,0,0,0,0,0,0,0,0,0,0,0,0,0,0,0,0,0,0,0,0,0,0,0,0,0,0,0,0,0,0,0,0,0,0,0,0,0,0,0,0,0,0,0,0,0,0,0,0,0,0],[-1,1,-1,-1,1,-1,1,-1,-1,-1,1,-1,1,-1,-1,1,-1,1,-1,1,-1,-1,-1,1,-1,1,-1,-1,1,-1,1,-1,1,-1,-1,-1,1,-1,1,-1,-1,1,-1,1,-1,1,-1,-1,-1,1,-1,1,-1,-1,1,-1,1,-1,1,-1,-1,1,-1,1,-1,-1,1,-1,1,-1,-1,1,-1,-1,-1,-1,1,-1,1,-1,-1,1,-1,-1,-1,1,4,5,-1,-1,1,4,5,-1,1,-1,1,-1,-1,1,-1,1,-1,-1,1,-1,1,-1,-1,1,-1,-1,-1,-1,1,-1,1,-1,-1,1,-1,-1,-1,1,4,5,-1,-1,1,4,5,-1,1,-1,1,-1,-1,1,-1,1,-1,-1,1,-1,1,-1,-1,1,-1,-1,-1,-1,1,-1,1,-1,-1,1,-1,-1,-1,1,4,5,-1,-1,1,4,5,-1,1,-1,1,-1,-1,1,-1,1,-1,-1,1,-1,1,-1,-1,1,-1,-1,1,-1,1,-1,-1,1,4,5,-1,-1,-1,1,-1,1,4,5,-1,1],[0,19,0,0,20,0,21,0,0,0,8,0,9,0,0,10,0,22,0,23,0,0,0,8,0,9,0,0,10,0,24,0,25,0,0,0,8,0,9,0,0,10,0,26,0,27,0,0,0,8,0,9,0,0,10,0,28,0,2,0,0,3,0,2,0,0,3,0,2,0,0,3,0,0,0,0,11,0,12,0,0,13,0,0,0,4,4,14,0,0,5,5,15,0,16,0,2,0,0,3,0,2,0,0,3,0,2,0,0,3,0,0,0,0,11,0,12,0,0,13,0,0,0,4,4,14,0,0,5,5,15,0,16,0,2,0,0,3,0,2,0,0,3,0,2,0,0,3,0,0,0,0,11,0,12,0,0,13,0,0,0,4,4,14,0,0,5,5,15,0,16,0,6,0,0,6,0,6,0,0,6,0,6,0,0,6,0,0,29,0,30,0,0,17,17,31,0,0,0,32,0,18,18,33,0,34]],[[{"name":"Garbage_ChuYu","rect":[3,702,215,354],"offset":[0,0],"originalSize":[215,354],"rotated":1,"capInsets":[0,0,0,0]}],[1],0,[0],[3],[1]],[[{"name":"Garbage_ZheDang","rect":[3,293,1006,126],"offset":[0,0],"originalSize":[1006,126],"capInsets":[0,0,0,0]}],[1],0,[0],[3],[1]],[[{"name":"icon_garbage_ChuYu","rect":[508,485,47,37],"offset":[0,0],"originalSize":[47,37],"capInsets":[0,0,0,0]}],[1],0,[0],[3],[7]],[[{"name":"Garbage_FenSiShu","rect":[773,1152,138,51],"offset":[0,0],"originalSize":[138,51],"rotated":1,"capInsets":[0,0,0,0]}],[1],0,[0],[3],[1]],[[{"name":"icon_garbage_HuiShou","rect":[508,443,52,36],"offset":[0,0],"originalSize":[52,36],"capInsets":[0,0,0,0]}],[1],0,[0],[3],[7]],[[{"name":"Garbage_HuiShou","rect":[3,923,215,354],"offset":[0,0],"originalSize":[215,354],"rotated":1,"capInsets":[0,0,0,0]}],[1],0,[0],[3],[1]],[[{"name":"Garbage_PeiFang1","rect":[470,565,371,360],"offset":[0,0],"originalSize":[371,360],"capInsets":[30,30,30,30]}],[1],0,[0],[3],[1]],[[{"name":"Garbage_PeiFang0","rect":[1048,1920,124,124],"offset":[0,0],"originalSize":[124,124],"capInsets":[0,0,0,0]}],[1],0,[0],[3],[1]],[[{"name":"Garbage_YouHai","rect":[1063,793,215,354],"offset":[0,0],"originalSize":[215,354],"rotated":1,"capInsets":[0,0,0,0]}],[1],0,[0],[3],[1]],[[{"name":"Garbage_DuiHuan","rect":[1265,1493,207,88],"offset":[0,0],"originalSize":[207,88],"rotated":1,"capInsets":[0,0,0,0]}],[1],0,[0],[3],[1]],[[{"name":"Garbage_Kuang2","rect":[185,1796,120,111],"offset":[0,0],"originalSize":[120,111],"rotated":1,"capInsets":[0,0,0,0]}],[1],0,[0],[3],[1]],[[{"name":"Garbage_QiTa","rect":[470,931,215,354],"offset":[0,0],"originalSize":[215,354],"rotated":1,"capInsets":[0,0,0,0]}],[1],0,[0],[3],[1]]]]