{"paths":{"0":["tyqRes/sources/VerifyRealName/x",0],"1":["tyqRes/sources/CrazyBox/duizhi",5],"2":["tyqRes/sources/OV_NativeAd/ui_sxxz2",0],"3":["tyqRes/sources/OV_NativeAd/ui_sxxz1",0],"4":["shiling",0],"5":["tyqRes/sources/VerifyRealName/wz2",0],"6":["tyqRes/sources/Privacypolicy/ui_gb",0],"7":["bg",0],"8":["tyqRes/sources/VerifyRealName/queren",0],"9":["tyqRes/sources/VerifyRealName/ming",0],"10":["pos",0],"11":["tyqRes/sources/VerifyRealName/yuanju",0],"12":["dot",0],"13":["tyqRes/sources/CrazyBox/ui_wz_fk",0],"14":["tyqRes/sources/Privacypolicy/ui_tyd",0],"15":["tyqRes/sources/Privacypolicy/ui_wz",0],"16":["tyqRes/sources/CrazyBox/par",0],"17":["x",0],"18":["tyqRes/sources/VerifyRealName/title",0],"19":["tyqRes/sources/Privacypolicy/ui_wxtsd",0],"20":["title",0],"21":["tyqRes/sources/AdCenter0fe8e2dab25c94017bd98635166d6c475ab681641",0],"22":["tyqRes/sources/CrazyBox/parDI",0],"23":["tyqRes/sources/VerifyRealName/haoma",0],"24":["tyqRes/sources/Privacypolicy/ui_1",0],"25":["tyqRes/sources/CrazyBox/ui_wz_fkdj",0],"26":["tyqRes/sources/VerifyRealName/juzhen",0],"27":["tyqRes/sources/OV_NativeAd/ui_gb_2",0],"28":["tyqRes/sources/Privacypolicy/ui_ty",0],"29":["tyqRes/sources/CrazyBox/ui_gj",0],"30":["logo",0],"31":["tyqRes/sources/CrazyBox/duizhi",0],"32":["tyqRes/sources/Privacypolicy/ui_jj",0],"33":["tyqRes/sources/VerifyRealName/wz3",0],"34":["tyqRes/sources/e7c698a41255bbe13ad0ce3acac4440",0],"35":["tyqRes/sources/Privacypolicy/ui_jjd",0],"36":["tyqRes/sources/CrazyBox/ui_gj",1,1],"37":["config",2],"38":["tyqRes/sources/Privacypolicy/ui_tyd",1,1],"39":["tyqRes/sources/CrazyBox/crazyBox",4],"40":["pos",1,1],"41":["tyqRes/prefab/LandPage",3],"42":["title",1,1],"43":["tyqRes/prefab/DartAd",3],"44":["tyqRes/sources/CrazyBox/ui_wz_fkdj",1,1],"45":["tyqRes/sources/AdCenter0fe8e2dab25c94017bd98635166d6c475ab681641",1,1],"46":["tyqRes/sources/VerifyRealName/queren",1,1],"47":["tyqRes/sources/VerifyRealName/ming",1,1],"48":["tyqRes/sources/Privacypolicy/ui_gb",1,1],"49":["tyqRes/sources/VerifyRealName/yuanju",1,1],"50":["bg",1,1],"51":["tyqRes/sources/OV_NativeAd/ui_gb_2",1,1],"52":["tyqRes/prefab/MiFeedAd",3],"54":["tyqRes/sources/OV_NativeAd/ui_sxxz2",1,1],"55":["tyqRes/sources/VerifyRealName/wz2",1,1],"56":["tyqRes/sources/VerifyRealName/juzhen",1,1],"58":["tyqRes/sources/OV_NativeAd/ui_sxxz1",1,1],"59":["tyqRes/sources/CrazyBox/par",1,1],"60":["tyqRes/prefab/Privacypolicy",3],"61":["tyqRes/sources/VerifyRealName/wz3",1,1],"62":["tyqRes/sources/VerifyRealName/title",1,1],"63":["tyqRes/sources/Privacypolicy/ui_jj",1,1],"64":["tyqRes/prefab/CrazyBox",3],"65":["tyqRes/prefab/OV_NativeAd",3],"66":["tyqRes/prefab/VerifyRealName",3],"67":["tyqRes/sources/e7c698a41255bbe13ad0ce3acac4440",1,1],"69":["tyqRes/sources/Privacypolicy/ui_wxtsd",1,1],"70":["tyqRes/sources/Privacypolicy/ui_jjd",1,1],"71":["tyqRes/sources/Privacypolicy/ui_wz",1,1],"72":["shiling",1,1],"73":["tyqRes/sources/CrazyBox/duizhi",6],"74":["tyqRes/sources/VerifyRealName/haoma",1,1],"75":["tyqRes/sources/Privacypolicy/ui_1",1,1],"76":["logo",1,1],"77":["x",1,1],"80":["tyqRes/sources/CrazyBox/parDI",1,1],"81":["tyqRes/sources/Privacypolicy/ui_ty",1,1],"83":["dot",1,1],"84":["tyqRes/sources/CrazyBox/duizhi",1,1],"85":["tyqRes/sources/VerifyRealName/x",1,1],"86":["tyqRes/sources/CrazyBox/ui_wz_fk",1,1]},"types":["cc.Texture2D","cc.SpriteFrame","cc.JsonAsset","cc.Prefab","cc.AnimationClip","cc.Asset","sp.SkeletonData"],"uuids":["03YgZcyvZFaZwEAvkwDuqh","0e4zcNZ9dHW71ziJvn0Juj","14RTu4V5FLz7gP6C0Ya0Qw","15ckSe6GJFMaRfhuIiRUZe","15dpuKdbtPcppPUQssaxqk","1e81PX/1xGJ73B7YBmVP6D","20TDCkOjRKvYiECldFbJbc","24EImUcX9P2IGYtxx2yTfE","26SPnQ6mhCIZ1yXvKT9xr9","2fKsz42JtPc560HTZOgeIe","36PaN34eBBiZExw45tBtuy","38CSuQvr5NCKSbkySoL49o","3aA2lAWRFB967ahqw3LLwa","4dWzEVO3FHOoslxnPFTpoI","54u86wTp5Frb3XCyh2bxmZ","5bmU8IKhFBWaUUypd1vTEH","66P5RzJdZJiYCoz18NnGtq","85xwdD++pD7rw79eBszlR1","8bFCNMZ45PZ4W0LKR2rYKu","8d0hWRXbpHtqk5gwE49xLg","a5FYK3e+VEN4TNaLgj5LEm","a8tCSjHH9AlLKEf8nMvRoh","b4JI7ypHxNwpXpafXCtCVv","bamuXApKxHVriknv4jX8O4","bbvJODBhJDFZOnQiHu7w+t","bcZEOlgMtMDbApIQUCI+52","bdZdX6Y5NPY7rbUwKjIh0E","c0Id0NG2lOrb7S2DFpu3iV","c3CWMOWDFN47mPCHDG+505","cfRoOqxwlEya6zcpGicbAD","d0N9eqVE5HYLDg2lbzytsS","d1DjpXSf9P+5jucBHqD12Q","d4KYXp/5VLYIm7hVYLTfHu","d5M0CO5/dEBKXJ5UIRv3W0","daQiQ2F4xAbqGtFu4H2+HK","e9tCljtMdG8b85dWX4oEZd","00tiY/A/VC2JXzXFAuk8Ag","05jGp2XR1DsbRasEZqDll6","05nPyV505D16fP6PFXHrjv","08owSQCepGlKo6qZQDmrNC","10Fg5lvthIs60YytmQItxA","13hgY+ERRBgrLuelSjSB/O","210sU9R0NE3ai9XnsdEJj2","23se+wldlALrjB56wxOQdf","27i7Wau29JTZyt7VFgPhjf","2a5xCe+n9I+rdJ0LAqEqiP","2cs/6wjuNJ87ybH4R7hn5x","2f0qo2P+FFvJkUlNPaGGPn","34FLUrhdhNOZaBWKmwY6/+","37tnOHB+NB/4LFmSMmb6Vm","43dHAxisBGy4y+LA8xUo3t","4f2j76kXZJZq7bd+i8xd54","56IAgxAsJBFq8+VM+jUzyN","61cyPdEfRN047sDK9rO0W5","64JsFo4rdCIoR8Xw7FBYNs","67iG3TXpRGqp0aGE9xIMHo","69RcptRYBFarBTJlKPwWLh","71VhFCTINJM6/Ky3oX9nBT","7dddrZiH9B64HANaOLWhVJ","90uTNIjRtDa6xpPzpJGD3Q","914+akk39BXpdNU9BifRyf","95pqpYI1ZAVotROOose1eL","a0OpSgpndCtbXlVGLPTKnr","a0TTj5U+tF/KM2Uigb9tlu","a9ROV+WmNME6W2ztZ7MUh1","aacHgEGqBJro8fzVeZy+Yo","ady6vT751LBou+CkAo0NPY","aep4JxTYFClqXOH8X/23SO","b4P/PCArtIdIH38t6mlw8Y","b5vFuhWFFDWoQwJL4x2m64","ba/4GlhxFBP6xaW0tx8xqo","bfELbjwUVMT4LS03tjgoHw","c0a67ze/NNgKFRYBoRWCHs","c3WJHW0gRP7r7Zcz3tasy5","c4qGJncbVN7KBrq6iAZ6M1","c5qEe8l4xDRLcgSbvZCnMh","c7Uh/VDhpNaLwGfR2gU1lT","d4VgMrxk9MO70VjTBf2GVR","d608qFRoFHwbXd0Dap056i","d8HsitJHxOYqo801xBk8ev","dcD4FUkZtNAapmMJz8jbyd","e6Jz/ArQtFNJzk+qAWVk2Z","e8Ueib+qJEhL6mXAHdnwbi","e9iKP/ykBO6KcT6E/qYR00","f29fBptt9M2pf2+/fdBBaj","fbwLroyJpF57lGk6CCNQZA","ff+mr9LxdLJpTnDDtiw03F","02delMVqdBD70a/HSD99FK","29FYIk+N1GYaeWH/q1NxQO","5cO7kybDxGj4ipyMYdRYZB","5f5dyqtRNNxaFmVzYns6FZ","7a/QZLET9IDreTiBfRn2PD","9bvaMerUlDyary99mJa6xp","a2MjXRFdtLlYQ5ouAFv/+R","e97GVMl6JHh5Ml5qEDdSGa","ecpdLyjvZBwrvm+cedCcQy","f0BIwQ8D5Ml7nTNQbh1YlS"],"scenes":{},"redirect":[87,0,91,0,95,0],"deps":["internal"],"packs":{"041df21ae":[36,39,44,59,64,80,86],"065e5b92f":[38,48,89,90,60,92,63,70,75,81],"06e8c1df5":[51,54,58,65],"0ad177e07":[0,2,3,4,5,6,7,8,9,10,11,12,13,14,15,53,16,57,17,18,19,20,21,22,68,23,24,25,26,27,28,29,30,31,32,33,78,79,34,82,35],"0c339d10f":[88,94,96],"0d9e13641":[45,52],"0e1e9df7c":[46,47,49,55,56,61,62,66,74,85]},"name":"resources","importBase":"import","nativeBase":"native","debug":false,"isZip":false,"encrypted":false,"versions":{"import":["041df21ae","860d4",37,"8860e","065e5b92f","d463c","06e8c1df5","e2f2e","0ad177e07","357eb","0c339d10f","a9ccb","0d9e13641","f177d","0e1e9df7c","e7563",1,"18c0b",40,"469dc",41,"15247",42,"80cf9",43,"73ee4",50,"4b951",93,"43d76",67,"9bbfd",69,"71c00",71,"e518b",72,"7d42a",73,"a2bc4",76,"9e99e",77,"808a1",83,"99c6f",84,"9f479"],"native":[0,"006cc",1,"1bbac",2,"7c6dc",3,"2bb6a",4,"b69b7",5,"ec678",6,"7f1c6",7,"99fbd",8,"e6042",9,"e370b",10,"2820d",11,"0a43b",12,"ce99b",13,"c7221",14,"73fec",15,"64717",53,"6d707",16,"60485",57,"c06a9",17,"0565f",18,"fdc98",19,"78a69",20,"ba1b0",21,"f405d",22,"d02b3",68,"83fcc",23,"7aabd",24,"d7ba6",25,"23140",26,"3eba6",27,"6b437",28,"7b823",29,"2c8d4",30,"95d7c",31,"70ee4",32,"e9869",33,"395b6",78,"d55c2",79,"cdbc9",34,"93113",82,"90cf4",35,"66e85"]}}